jamesbond/__init__.py
jamesbond/bonddata.py
jamesbond-0.0.15.dist-info/LICENSE
jamesbond-0.0.15.dist-info/METADATA
jamesbond-0.0.15.dist-info/WHEEL
jamesbond-0.0.15.dist-info/top_level.txt
jamesbond-0.0.15.dist-info/RECORD
