Metadata-Version: 2.1
Name: jamesbond
Version: 0.0.15
Summary: James Bond tabular data package in Pandas dataframe
Home-page: https://github.com/andrew-block/jamesbond
Author: Andrew Block
Author-email: andrewblock87@gmail.com
License: MIT
Download-URL: https://test.pypi.org/project/jamesbond/
Keywords: Bond,JamesBond,James Bond,007
Platform: UNKNOWN
Requires-Dist: pytest (==6.0.1)
Requires-Dist: pandas (==1.1.0)
